<?xml version='1.0' encoding='UTF-8' standalone='yes'?>
<assessmentResults xmlns='ets_extended_imsqti_v2p1' xmlns:xsi='http://www.w3.org/2001/XMLSchema-instance' xsi:schemaLocation='ets_extended_imsqti_v2p1 ./ets_extended_imsqti_v2p1.xsd http://www.imsglobal.org/xsd/imslip_v1p0 http://www.imsglobal.org/xsd/imslip_v1p0.xsd' xmlns:lip='http://www.imsglobal.org/xsd/imslip_v1p0'>
<assessmentResult xmlns="ets_extended_imsqti_v2p1"><context><lip:identification xmlns:lip="http://www.imsglobal.org/xsd/imslip_v1p0"><lip:contentype><lip:temporal><lip:temporalfield><lip:fieldlabel><lip:typename><lip:tyvalue>CTRID</lip:tyvalue></lip:typename></lip:fieldlabel><lip:fielddata>0036640640060008</lip:fielddata></lip:temporalfield></lip:temporal><lip:temporal><lip:temporalfield><lip:fieldlabel><lip:typename><lip:tyvalue>RegistrationSystemId</lip:tyvalue></lip:typename></lip:fieldlabel><lip:fielddata>HSEPBT</lip:fielddata></lip:temporalfield></lip:temporal><lip:temporal><lip:temporalfield><lip:fieldlabel><lip:typename><lip:tyvalue>RegistrationNumber</lip:tyvalue></lip:typename></lip:fieldlabel><lip:fielddata>344556414</lip:fielddata></lip:temporalfield></lip:temporal><lip:temporal><lip:temporalfield><lip:fieldlabel><lip:typename><lip:tyvalue>TestDate</lip:tyvalue></lip:typename></lip:fieldlabel><lip:fielddata>2014-04-11T08:26:44.989-04:00</lip:fielddata></lip:temporalfield></lip:temporal><lip:temporal><lip:temporalfield><lip:fieldlabel><lip:typename><lip:tyvalue>TestCenterAddressLine1</lip:tyvalue></lip:typename></lip:fieldlabel><lip:fielddata>541 MAIN STREET</lip:fielddata></lip:temporalfield></lip:temporal><lip:temporal><lip:temporalfield><lip:fieldlabel><lip:typename><lip:tyvalue>TestCenterCity</lip:tyvalue></lip:typename></lip:fieldlabel><lip:fielddata>NEW LONDON</lip:fielddata></lip:temporalfield></lip:temporal><lip:temporal><lip:temporalfield><lip:fieldlabel><lip:typename><lip:tyvalue>ETSTestCenterCountryCode</lip:tyvalue></lip:typename></lip:fieldlabel><lip:fielddata>USA</lip:fielddata></lip:temporalfield></lip:temporal><lip:temporal><lip:temporalfield><lip:fieldlabel><lip:typename><lip:tyvalue>TestCenterName</lip:tyvalue></lip:typename></lip:fieldlabel><lip:fielddata>COLBY-SAWYER COLLEGE (PAPER)</lip:fielddata></lip:temporalfield></lip:temporal><lip:temporal><lip:temporalfield><lip:fieldlabel><lip:typename><lip:tyvalue>TestCenterPostalCode</lip:tyvalue></lip:typename></lip:fieldlabel><lip:fielddata>03257</lip:fielddata></lip:temporalfield></lip:temporal><lip:temporal><lip:temporalfield><lip:fieldlabel><lip:typename><lip:tyvalue>TestCenterStateProvince</lip:tyvalue></lip:typename></lip:fieldlabel><lip:fielddata>NH</lip:fielddata></lip:temporalfield></lip:temporal><lip:temporal><lip:temporalfield><lip:fieldlabel><lip:typename><lip:tyvalue>TestCenterCode</lip:tyvalue></lip:typename></lip:fieldlabel><lip:fielddata>HSTP10011A</lip:fielddata></lip:temporalfield></lip:temporal><lip:temporal><lip:temporalfield><lip:fieldlabel><lip:typename><lip:tyvalue>TestCenterTimeZone</lip:tyvalue></lip:typename></lip:fieldlabel><lip:fielddata>-04:00</lip:fielddata></lip:temporalfield></lip:temporal><lip:temporal><lip:temporalfield><lip:fieldlabel><lip:typename><lip:tyvalue>AdminCode</lip:tyvalue></lip:typename></lip:fieldlabel><lip:fielddata>20140101B</lip:fielddata></lip:temporalfield></lip:temporal><lip:temporal><lip:temporalfield><lip:fieldlabel><lip:typename><lip:tyvalue>ProgramCode</lip:tyvalue></lip:typename></lip:fieldlabel><lip:fielddata>HSE</lip:fielddata></lip:temporalfield></lip:temporal><lip:temporal><lip:temporalfield><lip:fieldlabel><lip:typename><lip:tyvalue>TestCode</lip:tyvalue></lip:typename></lip:fieldlabel><lip:fielddata>902</lip:fielddata></lip:temporalfield></lip:temporal><lip:temporal><lip:temporalfield><lip:fieldlabel><lip:typename><lip:tyvalue>TEST_PKG</lip:tyvalue></lip:typename></lip:fieldlabel><lip:fielddata>HSE902PPT00053604PKG000</lip:fielddata></lip:temporalfield></lip:temporal><lip:temporal><lip:temporalfield><lip:fieldlabel><lip:typename><lip:tyvalue>SUBFORM</lip:tyvalue></lip:typename></lip:fieldlabel><lip:fielddata>000006-02-0000000001</lip:fielddata></lip:temporalfield></lip:temporal><lip:temporal><lip:temporalfield><lip:fieldlabel><lip:typename><lip:tyvalue>SystemFormCode</lip:tyvalue></lip:typename></lip:fieldlabel><lip:fielddata>143121</lip:fielddata></lip:temporalfield></lip:temporal><lip:temporal><lip:temporalfield><lip:fieldlabel><lip:typename><lip:tyvalue>DeliveryMode</lip:tyvalue></lip:typename></lip:fieldlabel><lip:fielddata>PBT</lip:fielddata></lip:temporalfield></lip:temporal><lip:temporal><lip:temporalfield><lip:fieldlabel><lip:typename><lip:tyvalue>OperationalCRCountReportedToRatingSystem</lip:tyvalue></lip:typename></lip:fieldlabel><lip:fielddata>0</lip:fielddata></lip:temporalfield></lip:temporal><lip:temporal><lip:temporalfield><lip:fieldlabel><lip:typename><lip:tyvalue>NonOperationalCRCountReportedToRatingSystem</lip:tyvalue></lip:typename></lip:fieldlabel><lip:fielddata>0</lip:fielddata></lip:temporalfield></lip:temporal><lip:temporal><lip:temporalfield><lip:fieldlabel><lip:typename><lip:tyvalue>CandidateScoreStatus</lip:tyvalue></lip:typename></lip:fieldlabel><lip:fielddata>RPTBL</lip:fielddata></lip:temporalfield></lip:temporal><lip:temporal><lip:temporalfield><lip:fieldlabel><lip:typename><lip:tyvalue>ScoreIndicator</lip:tyvalue></lip:typename></lip:fieldlabel><lip:fielddata>1</lip:fielddata></lip:temporalfield></lip:temporal></lip:contentype><lip:ext_identification><lip:address><lip:pobox /><lip:street /></lip:address><lip:demographics /></lip:ext_identification></lip:identification></context><testResult identifier="20140101B"><outcomeVariable baseType="integer" cardinality="single" identifier="TerminationType"><value fieldIdentifier="0036640640060008" /></outcomeVariable><outcomeVariable baseType="integer" cardinality="single" identifier="TerminationType"><value fieldIdentifier="000006-02-0000000001" /></outcomeVariable><outcomeVariable baseType="integer" cardinality="single" identifier="TerminationType"><value fieldIdentifier="1" /></outcomeVariable><outcomeVariable identifier="Numbers" normalMinimum="0" normalMaximum="13" cardinality="single" baseType="float"><value fieldIdentifier="002">3</value></outcomeVariable><outcomeVariable identifier="Geometry" normalMinimum="0" normalMaximum="13" cardinality="single" baseType="float"><value fieldIdentifier="003">4</value></outcomeVariable><outcomeVariable identifier="Prob" normalMinimum="0" normalMaximum="14" cardinality="single" baseType="float"><value fieldIdentifier="004">0</value></outcomeVariable><outcomeVariable identifier="Algebra" normalMinimum="0" normalMaximum="10" cardinality="single" baseType="float"><value fieldIdentifier="005">1</value></outcomeVariable><outcomeVariable identifier="Total" normalMinimum="0" normalMaximum="50" cardinality="single" baseType="float"><value fieldIdentifier="050">8</value></outcomeVariable><outcomeVariable identifier="Total_SA" normalMinimum="1" normalMaximum="20" cardinality="single" baseType="float"><value fieldIdentifier="150">3</value></outcomeVariable><outcomeVariable identifier="Num_NA" normalMinimum="0" normalMaximum="13" cardinality="single" baseType="float"><value fieldIdentifier="151">13</value></outcomeVariable><outcomeVariable identifier="Geom_NA" normalMinimum="0" normalMaximum="13" cardinality="single" baseType="float"><value fieldIdentifier="152">13</value></outcomeVariable><outcomeVariable identifier="Prob_NA" normalMinimum="0" normalMaximum="14" cardinality="single" baseType="float"><value fieldIdentifier="153">14</value></outcomeVariable><outcomeVariable identifier="Alg_NA" normalMinimum="0" normalMaximum="10" cardinality="single" baseType="float"><value fieldIdentifier="154">10</value></outcomeVariable><outcomeVariable identifier="PF_MC" normalMinimum="0" normalMaximum="1" cardinality="single" baseType="float"><value fieldIdentifier="501">0</value></outcomeVariable><outcomeVariable identifier="CL_RGDY" normalMinimum="0" normalMaximum="1" cardinality="single" baseType="float"><value fieldIdentifier="502">0</value></outcomeVariable><outcomeVariable identifier="Scale_CR" normalMinimum="1" normalMaximum="20" cardinality="single" baseType="float"><value fieldIdentifier="600">3</value></outcomeVariable></testResult><itemResult identifier="VF881684" datestamp="2014-01-01T00:00:00Z" sessionStatus="final"><responseVariable identifier="CandidateResponse" cardinality="single" baseType="integer"><candidateResponse><value>2</value></candidateResponse></responseVariable><outcomeVariable identifier="EditCode" cardinality="single" baseType="integer"><value>0</value></outcomeVariable><outcomeVariable identifier="Score" cardinality="single" baseType="integer"><value>0.00</value></outcomeVariable></itemResult><itemResult identifier="VF881707" datestamp="2014-01-01T00:00:00Z" sessionStatus="final"><responseVariable identifier="CandidateResponse" cardinality="single" baseType="integer"><candidateResponse><value>2</value></candidateResponse></responseVariable><outcomeVariable identifier="EditCode" cardinality="single" baseType="integer"><value>1</value></outcomeVariable><outcomeVariable identifier="Score" cardinality="single" baseType="integer"><value>1</value></outcomeVariable></itemResult><itemResult identifier="VF882669" datestamp="2014-01-01T00:00:00Z" sessionStatus="final"><responseVariable identifier="CandidateResponse" cardinality="single" baseType="integer"><candidateResponse><value>2</value></candidateResponse></responseVariable><outcomeVariable identifier="EditCode" cardinality="single" baseType="integer"><value>0</value></outcomeVariable><outcomeVariable identifier="Score" cardinality="single" baseType="integer"><value>0.00</value></outcomeVariable></itemResult><itemResult identifier="VF881709" datestamp="2014-01-01T00:00:00Z" sessionStatus="final"><responseVariable identifier="CandidateResponse" cardinality="single" baseType="integer"><candidateResponse><value>2</value></candidateResponse></responseVariable><outcomeVariable identifier="EditCode" cardinality="single" baseType="integer"><value>0</value></outcomeVariable><outcomeVariable identifier="Score" cardinality="single" baseType="integer"><value>0.00</value></outcomeVariable></itemResult><itemResult identifier="VF881830" datestamp="2014-01-01T00:00:00Z" sessionStatus="final"><responseVariable identifier="CandidateResponse" cardinality="single" baseType="integer"><candidateResponse><value>2</value></candidateResponse></responseVariable><outcomeVariable identifier="EditCode" cardinality="single" baseType="integer"><value>0</value></outcomeVariable><outcomeVariable identifier="Score" cardinality="single" baseType="integer"><value>0.00</value></outcomeVariable></itemResult><itemResult identifier="VF881825" datestamp="2014-01-01T00:00:00Z" sessionStatus="final"><responseVariable identifier="CandidateResponse" cardinality="single" baseType="integer"><candidateResponse><value>2</value></candidateResponse></responseVariable><outcomeVariable identifier="EditCode" cardinality="single" baseType="integer"><value>0</value></outcomeVariable><outcomeVariable identifier="Score" cardinality="single" baseType="integer"><value>0.00</value></outcomeVariable></itemResult><itemResult identifier="VF881005" datestamp="2014-01-01T00:00:00Z" sessionStatus="final"><responseVariable identifier="CandidateResponse" cardinality="single" baseType="integer"><candidateResponse><value>2</value></candidateResponse></responseVariable><outcomeVariable identifier="EditCode" cardinality="single" baseType="integer"><value>0</value></outcomeVariable><outcomeVariable identifier="Score" cardinality="single" baseType="integer"><value>0.00</value></outcomeVariable></itemResult><itemResult identifier="VF881006" datestamp="2014-01-01T00:00:00Z" sessionStatus="final"><responseVariable identifier="CandidateResponse" cardinality="single" baseType="integer"><candidateResponse><value>2</value></candidateResponse></responseVariable><outcomeVariable identifier="EditCode" cardinality="single" baseType="integer"><value>0</value></outcomeVariable><outcomeVariable identifier="Score" cardinality="single" baseType="integer"><value>0.00</value></outcomeVariable></itemResult><itemResult identifier="VF881004" datestamp="2014-01-01T00:00:00Z" sessionStatus="final"><responseVariable identifier="CandidateResponse" cardinality="single" baseType="integer"><candidateResponse><value>2</value></candidateResponse></responseVariable><outcomeVariable identifier="EditCode" cardinality="single" baseType="integer"><value>0</value></outcomeVariable><outcomeVariable identifier="Score" cardinality="single" baseType="integer"><value>0.00</value></outcomeVariable></itemResult><itemResult identifier="VF882581" datestamp="2014-01-01T00:00:00Z" sessionStatus="final"><responseVariable identifier="CandidateResponse" cardinality="single" baseType="integer"><candidateResponse><value>2</value></candidateResponse></responseVariable><outcomeVariable identifier="EditCode" cardinality="single" baseType="integer"><value>0</value></outcomeVariable><outcomeVariable identifier="Score" cardinality="single" baseType="integer"><value>0.00</value></outcomeVariable></itemResult><itemResult identifier="VF881587" datestamp="2014-01-01T00:00:00Z" sessionStatus="final"><responseVariable identifier="CandidateResponse" cardinality="single" baseType="integer"><candidateResponse><value>1</value></candidateResponse></responseVariable><outcomeVariable identifier="EditCode" cardinality="single" baseType="integer"><value>0</value></outcomeVariable><outcomeVariable identifier="Score" cardinality="single" baseType="integer"><value>0.00</value></outcomeVariable></itemResult><itemResult identifier="VF881840" datestamp="2014-01-01T00:00:00Z" sessionStatus="final"><responseVariable identifier="CandidateResponse" cardinality="single" baseType="integer"><candidateResponse><value>1</value></candidateResponse></responseVariable><outcomeVariable identifier="EditCode" cardinality="single" baseType="integer"><value>0</value></outcomeVariable><outcomeVariable identifier="Score" cardinality="single" baseType="integer"><value>0.00</value></outcomeVariable></itemResult><itemResult identifier="VF881638" datestamp="2014-01-01T00:00:00Z" sessionStatus="final"><responseVariable identifier="CandidateResponse" cardinality="single" baseType="integer"><candidateResponse><value>1</value></candidateResponse></responseVariable><outcomeVariable identifier="EditCode" cardinality="single" baseType="integer"><value>0</value></outcomeVariable><outcomeVariable identifier="Score" cardinality="single" baseType="integer"><value>0.00</value></outcomeVariable></itemResult><itemResult identifier="VF881691" datestamp="2014-01-01T00:00:00Z" sessionStatus="final"><responseVariable identifier="CandidateResponse" cardinality="single" baseType="integer"><candidateResponse><value>1</value></candidateResponse></responseVariable><outcomeVariable identifier="EditCode" cardinality="single" baseType="integer"><value>1</value></outcomeVariable><outcomeVariable identifier="Score" cardinality="single" baseType="integer"><value>1</value></outcomeVariable></itemResult><itemResult identifier="VF881529" datestamp="2014-01-01T00:00:00Z" sessionStatus="final"><responseVariable identifier="CandidateResponse" cardinality="single" baseType="integer"><candidateResponse><value>1</value></candidateResponse></responseVariable><outcomeVariable identifier="EditCode" cardinality="single" baseType="integer"><value>0</value></outcomeVariable><outcomeVariable identifier="Score" cardinality="single" baseType="integer"><value>0.00</value></outcomeVariable></itemResult><itemResult identifier="VF881530" datestamp="2014-01-01T00:00:00Z" sessionStatus="final"><responseVariable identifier="CandidateResponse" cardinality="single" baseType="integer"><candidateResponse><value>1</value></candidateResponse></responseVariable><outcomeVariable identifier="EditCode" cardinality="single" baseType="integer"><value>0</value></outcomeVariable><outcomeVariable identifier="Score" cardinality="single" baseType="integer"><value>0.00</value></outcomeVariable></itemResult><itemResult identifier="VF882008" datestamp="2014-01-01T00:00:00Z" sessionStatus="final"><responseVariable identifier="CandidateResponse" cardinality="single" baseType="integer"><candidateResponse><value>1</value></candidateResponse></responseVariable><outcomeVariable identifier="EditCode" cardinality="single" baseType="integer"><value>1</value></outcomeVariable><outcomeVariable identifier="Score" cardinality="single" baseType="integer"><value>1</value></outcomeVariable></itemResult><itemResult identifier="VF882006" datestamp="2014-01-01T00:00:00Z" sessionStatus="final"><responseVariable identifier="CandidateResponse" cardinality="single" baseType="integer"><candidateResponse><value>1</value></candidateResponse></responseVariable><outcomeVariable identifier="EditCode" cardinality="single" baseType="integer"><value>0</value></outcomeVariable><outcomeVariable identifier="Score" cardinality="single" baseType="integer"><value>0.00</value></outcomeVariable></itemResult><itemResult identifier="VF882005" datestamp="2014-01-01T00:00:00Z" sessionStatus="final"><responseVariable identifier="CandidateResponse" cardinality="single" baseType="integer"><candidateResponse><value>1</value></candidateResponse></responseVariable><outcomeVariable identifier="EditCode" cardinality="single" baseType="integer"><value>0</value></outcomeVariable><outcomeVariable identifier="Score" cardinality="single" baseType="integer"><value>0.00</value></outcomeVariable></itemResult><itemResult identifier="VF882009" datestamp="2014-01-01T00:00:00Z" sessionStatus="final"><responseVariable identifier="CandidateResponse" cardinality="single" baseType="integer"><candidateResponse><value>1</value></candidateResponse></responseVariable><outcomeVariable identifier="EditCode" cardinality="single" baseType="integer"><value>0</value></outcomeVariable><outcomeVariable identifier="Score" cardinality="single" baseType="integer"><value>0.00</value></outcomeVariable></itemResult><itemResult identifier="VF882007" datestamp="2014-01-01T00:00:00Z" sessionStatus="final"><responseVariable identifier="CandidateResponse" cardinality="single" baseType="integer"><candidateResponse><value>1</value></candidateResponse></responseVariable><outcomeVariable identifier="EditCode" cardinality="single" baseType="integer"><value>0</value></outcomeVariable><outcomeVariable identifier="Score" cardinality="single" baseType="integer"><value>0.00</value></outcomeVariable></itemResult><itemResult identifier="VF882004" datestamp="2014-01-01T00:00:00Z" sessionStatus="final"><responseVariable identifier="CandidateResponse" cardinality="single" baseType="integer"><candidateResponse><value>1</value></candidateResponse></responseVariable><outcomeVariable identifier="EditCode" cardinality="single" baseType="integer"><value>0</value></outcomeVariable><outcomeVariable identifier="Score" cardinality="single" baseType="integer"><value>0.00</value></outcomeVariable></itemResult><itemResult identifier="VF881843" datestamp="2014-01-01T00:00:00Z" sessionStatus="final"><responseVariable identifier="CandidateResponse" cardinality="single" baseType="integer"><candidateResponse><value>1</value></candidateResponse></responseVariable><outcomeVariable identifier="EditCode" cardinality="single" baseType="integer"><value>1</value></outcomeVariable><outcomeVariable identifier="Score" cardinality="single" baseType="integer"><value>1</value></outcomeVariable></itemResult><itemResult identifier="VF881657" datestamp="2014-01-01T00:00:00Z" sessionStatus="final"><responseVariable identifier="CandidateResponse" cardinality="single" baseType="integer"><candidateResponse><value>1</value></candidateResponse></responseVariable><outcomeVariable identifier="EditCode" cardinality="single" baseType="integer"><value>0</value></outcomeVariable><outcomeVariable identifier="Score" cardinality="single" baseType="integer"><value>0.00</value></outcomeVariable></itemResult><itemResult identifier="VF882683" datestamp="2014-01-01T00:00:00Z" sessionStatus="final"><responseVariable identifier="CandidateResponse" cardinality="single" baseType="integer"><candidateResponse><value>1</value></candidateResponse></responseVariable><outcomeVariable identifier="EditCode" cardinality="single" baseType="integer"><value>1</value></outcomeVariable><outcomeVariable identifier="Score" cardinality="single" baseType="integer"><value>1</value></outcomeVariable></itemResult><itemResult identifier="VF882571" datestamp="2014-01-01T00:00:00Z" sessionStatus="final"><responseVariable identifier="CandidateResponse" cardinality="single" baseType="integer"><candidateResponse><value>1</value></candidateResponse></responseVariable><outcomeVariable identifier="EditCode" cardinality="single" baseType="integer"><value>0</value></outcomeVariable><outcomeVariable identifier="Score" cardinality="single" baseType="integer"><value>0.00</value></outcomeVariable></itemResult><itemResult identifier="VF881667" datestamp="2014-01-01T00:00:00Z" sessionStatus="final"><responseVariable identifier="CandidateResponse" cardinality="single" baseType="integer"><candidateResponse><value>1</value></candidateResponse></responseVariable><outcomeVariable identifier="EditCode" cardinality="single" baseType="integer"><value>0</value></outcomeVariable><outcomeVariable identifier="Score" cardinality="single" baseType="integer"><value>0.00</value></outcomeVariable></itemResult><itemResult identifier="VF881578" datestamp="2014-01-01T00:00:00Z" sessionStatus="final"><responseVariable identifier="CandidateResponse" cardinality="single" baseType="integer"><candidateResponse><value>1</value></candidateResponse></responseVariable><outcomeVariable identifier="EditCode" cardinality="single" baseType="integer"><value>1</value></outcomeVariable><outcomeVariable identifier="Score" cardinality="single" baseType="integer"><value>1</value></outcomeVariable></itemResult><itemResult identifier="VF882523" datestamp="2014-01-01T00:00:00Z" sessionStatus="final"><responseVariable identifier="CandidateResponse" cardinality="single" baseType="integer"><candidateResponse><value>1</value></candidateResponse></responseVariable><outcomeVariable identifier="EditCode" cardinality="single" baseType="integer"><value>1</value></outcomeVariable><outcomeVariable identifier="Score" cardinality="single" baseType="integer"><value>1</value></outcomeVariable></itemResult><itemResult identifier="VF882522" datestamp="2014-01-01T00:00:00Z" sessionStatus="final"><responseVariable identifier="CandidateResponse" cardinality="single" baseType="integer"><candidateResponse><value>1</value></candidateResponse></responseVariable><outcomeVariable identifier="EditCode" cardinality="single" baseType="integer"><value>0</value></outcomeVariable><outcomeVariable identifier="Score" cardinality="single" baseType="integer"><value>0.00</value></outcomeVariable></itemResult><itemResult identifier="VF881681" datestamp="2014-01-01T00:00:00Z" sessionStatus="final"><responseVariable identifier="CandidateResponse" cardinality="single" baseType="integer"><candidateResponse><value>4</value></candidateResponse></responseVariable><outcomeVariable identifier="EditCode" cardinality="single" baseType="integer"><value>1</value></outcomeVariable><outcomeVariable identifier="Score" cardinality="single" baseType="integer"><value>1</value></outcomeVariable></itemResult><itemResult identifier="VF907116" datestamp="2014-01-01T00:00:00Z" sessionStatus="final"><responseVariable identifier="CandidateResponse" cardinality="single" baseType="integer"><candidateResponse><value>4</value></candidateResponse></responseVariable><outcomeVariable identifier="EditCode" cardinality="single" baseType="integer"><value>0</value></outcomeVariable><outcomeVariable identifier="Score" cardinality="single" baseType="integer"><value>0.00</value></outcomeVariable></itemResult><itemResult identifier="VF881647" datestamp="2014-01-01T00:00:00Z" sessionStatus="final"><responseVariable identifier="CandidateResponse" cardinality="single" baseType="integer"><candidateResponse><value>4</value></candidateResponse></responseVariable><outcomeVariable identifier="EditCode" cardinality="single" baseType="integer"><value>0</value></outcomeVariable><outcomeVariable identifier="Score" cardinality="single" baseType="integer"><value>0.00</value></outcomeVariable></itemResult><itemResult identifier="VF881643" datestamp="2014-01-01T00:00:00Z" sessionStatus="final"><responseVariable identifier="CandidateResponse" cardinality="single" baseType="integer"><candidateResponse><value>4</value></candidateResponse></responseVariable><outcomeVariable identifier="EditCode" cardinality="single" baseType="integer"><value>0</value></outcomeVariable><outcomeVariable identifier="Score" cardinality="single" baseType="integer"><value>0.00</value></outcomeVariable></itemResult><itemResult identifier="VF882651" datestamp="2014-01-01T00:00:00Z" sessionStatus="final"><responseVariable identifier="CandidateResponse" cardinality="single" baseType="integer"><candidateResponse><value>4</value></candidateResponse></responseVariable><outcomeVariable identifier="EditCode" cardinality="single" baseType="integer"><value>0</value></outcomeVariable><outcomeVariable identifier="Score" cardinality="single" baseType="integer"><value>0.00</value></outcomeVariable></itemResult><itemResult identifier="VF882608" datestamp="2014-01-01T00:00:00Z" sessionStatus="final"><responseVariable identifier="CandidateResponse" cardinality="single" baseType="integer"><candidateResponse><value>4</value></candidateResponse></responseVariable><outcomeVariable identifier="EditCode" cardinality="single" baseType="integer"><value>0</value></outcomeVariable><outcomeVariable identifier="Score" cardinality="single" baseType="integer"><value>0.00</value></outcomeVariable></itemResult><itemResult identifier="VF882470" datestamp="2014-01-01T00:00:00Z" sessionStatus="final"><responseVariable identifier="CandidateResponse" cardinality="single" baseType="integer"><candidateResponse><value>4</value></candidateResponse></responseVariable><outcomeVariable identifier="EditCode" cardinality="single" baseType="integer"><value>0</value></outcomeVariable><outcomeVariable identifier="Score" cardinality="single" baseType="integer"><value>0.00</value></outcomeVariable></itemResult><itemResult identifier="VF882468" datestamp="2014-01-01T00:00:00Z" sessionStatus="final"><responseVariable identifier="CandidateResponse" cardinality="single" baseType="integer"><candidateResponse><value>4</value></candidateResponse></responseVariable><outcomeVariable identifier="EditCode" cardinality="single" baseType="integer"><value>0</value></outcomeVariable><outcomeVariable identifier="Score" cardinality="single" baseType="integer"><value>0.00</value></outcomeVariable></itemResult><itemResult identifier="VF882469" datestamp="2014-01-01T00:00:00Z" sessionStatus="final"><responseVariable identifier="CandidateResponse" cardinality="single" baseType="integer"><candidateResponse><value>4</value></candidateResponse></responseVariable><outcomeVariable identifier="EditCode" cardinality="single" baseType="integer"><value>0</value></outcomeVariable><outcomeVariable identifier="Score" cardinality="single" baseType="integer"><value>0.00</value></outcomeVariable></itemResult><itemResult identifier="VF882583" datestamp="2014-01-01T00:00:00Z" sessionStatus="final"><responseVariable identifier="CandidateResponse" cardinality="single" baseType="integer"><candidateResponse><value>4</value></candidateResponse></responseVariable><outcomeVariable identifier="EditCode" cardinality="single" baseType="integer"><value>0</value></outcomeVariable><outcomeVariable identifier="Score" cardinality="single" baseType="integer"><value>0.00</value></outcomeVariable></itemResult><itemResult identifier="VF882645" datestamp="2014-01-01T00:00:00Z" sessionStatus="final"><responseVariable identifier="CandidateResponse" cardinality="single" baseType="integer"><candidateResponse><value>5</value></candidateResponse></responseVariable><outcomeVariable identifier="EditCode" cardinality="single" baseType="integer"><value>0</value></outcomeVariable><outcomeVariable identifier="Score" cardinality="single" baseType="integer"><value>0.00</value></outcomeVariable></itemResult><itemResult identifier="VF882656" datestamp="2014-01-01T00:00:00Z" sessionStatus="final"><responseVariable identifier="CandidateResponse" cardinality="single" baseType="integer"><candidateResponse><value>5</value></candidateResponse></responseVariable><outcomeVariable identifier="EditCode" cardinality="single" baseType="integer"><value>0</value></outcomeVariable><outcomeVariable identifier="Score" cardinality="single" baseType="integer"><value>0.00</value></outcomeVariable></itemResult><itemResult identifier="VF882611" datestamp="2014-01-01T00:00:00Z" sessionStatus="final"><responseVariable identifier="CandidateResponse" cardinality="single" baseType="integer"><candidateResponse><value>5</value></candidateResponse></responseVariable><outcomeVariable identifier="EditCode" cardinality="single" baseType="integer"><value>0</value></outcomeVariable><outcomeVariable identifier="Score" cardinality="single" baseType="integer"><value>0.00</value></outcomeVariable></itemResult><itemResult identifier="VF882181" datestamp="2014-01-01T00:00:00Z" sessionStatus="final"><responseVariable identifier="CandidateResponse" cardinality="single" baseType="integer"><candidateResponse><value>5</value></candidateResponse></responseVariable><outcomeVariable identifier="EditCode" cardinality="single" baseType="integer"><value>0</value></outcomeVariable><outcomeVariable identifier="Score" cardinality="single" baseType="integer"><value>0.00</value></outcomeVariable></itemResult><itemResult identifier="VF882180" datestamp="2014-01-01T00:00:00Z" sessionStatus="final"><responseVariable identifier="CandidateResponse" cardinality="single" baseType="integer"><candidateResponse><value>5</value></candidateResponse></responseVariable><outcomeVariable identifier="EditCode" cardinality="single" baseType="integer"><value>0</value></outcomeVariable><outcomeVariable identifier="Score" cardinality="single" baseType="integer"><value>0.00</value></outcomeVariable></itemResult><itemResult identifier="VF882182" datestamp="2014-01-01T00:00:00Z" sessionStatus="final"><responseVariable identifier="CandidateResponse" cardinality="single" baseType="integer"><candidateResponse><value>5</value></candidateResponse></responseVariable><outcomeVariable identifier="EditCode" cardinality="single" baseType="integer"><value>0</value></outcomeVariable><outcomeVariable identifier="Score" cardinality="single" baseType="integer"><value>0.00</value></outcomeVariable></itemResult><itemResult identifier="VF882584" datestamp="2014-01-01T00:00:00Z" sessionStatus="final"><responseVariable identifier="CandidateResponse" cardinality="single" baseType="integer"><candidateResponse><value>5</value></candidateResponse></responseVariable><outcomeVariable identifier="EditCode" cardinality="single" baseType="integer"><value>0</value></outcomeVariable><outcomeVariable identifier="Score" cardinality="single" baseType="integer"><value>0.00</value></outcomeVariable></itemResult><itemResult identifier="VF882601" datestamp="2014-01-01T00:00:00Z" sessionStatus="final"><responseVariable identifier="CandidateResponse" cardinality="single" baseType="integer"><candidateResponse><value>5</value></candidateResponse></responseVariable><outcomeVariable identifier="EditCode" cardinality="single" baseType="integer"><value>0</value></outcomeVariable><outcomeVariable identifier="Score" cardinality="single" baseType="integer"><value>0.00</value></outcomeVariable></itemResult><itemResult identifier="VF881292" datestamp="2014-01-01T00:00:00Z" sessionStatus="final"><responseVariable identifier="CandidateResponse" cardinality="single" baseType="integer"><candidateResponse><value>5</value></candidateResponse></responseVariable><outcomeVariable identifier="EditCode" cardinality="single" baseType="integer"><value>0</value></outcomeVariable><outcomeVariable identifier="Score" cardinality="single" baseType="integer"><value>0.00</value></outcomeVariable></itemResult><itemResult identifier="VF881291" datestamp="2014-01-01T00:00:00Z" sessionStatus="final"><responseVariable identifier="CandidateResponse" cardinality="single" baseType="integer"><candidateResponse><value>5</value></candidateResponse></responseVariable><outcomeVariable identifier="EditCode" cardinality="single" baseType="integer"><value>0</value></outcomeVariable><outcomeVariable identifier="Score" cardinality="single" baseType="integer"><value>0.00</value></outcomeVariable></itemResult></assessmentResult>
<assessmentResult xmlns="ets_extended_imsqti_v2p1"><context><lip:identification xmlns:lip="http://www.imsglobal.org/xsd/imslip_v1p0"><lip:contentype><lip:temporal><lip:temporalfield><lip:fieldlabel><lip:typename><lip:tyvalue>CTRID</lip:tyvalue></lip:typename></lip:fieldlabel><lip:fielddata>0036630640060010</lip:fielddata></lip:temporalfield></lip:temporal><lip:temporal><lip:temporalfield><lip:fieldlabel><lip:typename><lip:tyvalue>RegistrationSystemId</lip:tyvalue></lip:typename></lip:fieldlabel><lip:fielddata>HSEPBT</lip:fielddata></lip:temporalfield></lip:temporal><lip:temporal><lip:temporalfield><lip:fieldlabel><lip:typename><lip:tyvalue>RegistrationNumber</lip:tyvalue></lip:typename></lip:fieldlabel><lip:fielddata>803356714</lip:fielddata></lip:temporalfield></lip:temporal><lip:temporal><lip:temporalfield><lip:fieldlabel><lip:typename><lip:tyvalue>TestDate</lip:tyvalue></lip:typename></lip:fieldlabel><lip:fielddata>2014-04-11T08:26:48.437-04:00</lip:fielddata></lip:temporalfield></lip:temporal><lip:temporal><lip:temporalfield><lip:fieldlabel><lip:typename><lip:tyvalue>TestCenterAddressLine1</lip:tyvalue></lip:typename></lip:fieldlabel><lip:fielddata>541 MAIN STREET</lip:fielddata></lip:temporalfield></lip:temporal><lip:temporal><lip:temporalfield><lip:fieldlabel><lip:typename><lip:tyvalue>TestCenterCity</lip:tyvalue></lip:typename></lip:fieldlabel><lip:fielddata>NEW LONDON</lip:fielddata></lip:temporalfield></lip:temporal><lip:temporal><lip:temporalfield><lip:fieldlabel><lip:typename><lip:tyvalue>ETSTestCenterCountryCode</lip:tyvalue></lip:typename></lip:fieldlabel><lip:fielddata>USA</lip:fielddata></lip:temporalfield></lip:temporal><lip:temporal><lip:temporalfield><lip:fieldlabel><lip:typename><lip:tyvalue>TestCenterName</lip:tyvalue></lip:typename></lip:fieldlabel><lip:fielddata>COLBY-SAWYER COLLEGE (PAPER)</lip:fielddata></lip:temporalfield></lip:temporal><lip:temporal><lip:temporalfield><lip:fieldlabel><lip:typename><lip:tyvalue>TestCenterPostalCode</lip:tyvalue></lip:typename></lip:fieldlabel><lip:fielddata>03257</lip:fielddata></lip:temporalfield></lip:temporal><lip:temporal><lip:temporalfield><lip:fieldlabel><lip:typename><lip:tyvalue>TestCenterStateProvince</lip:tyvalue></lip:typename></lip:fieldlabel><lip:fielddata>NH</lip:fielddata></lip:temporalfield></lip:temporal><lip:temporal><lip:temporalfield><lip:fieldlabel><lip:typename><lip:tyvalue>TestCenterCode</lip:tyvalue></lip:typename></lip:fieldlabel><lip:fielddata>HSTP10011A</lip:fielddata></lip:temporalfield></lip:temporal><lip:temporal><lip:temporalfield><lip:fieldlabel><lip:typename><lip:tyvalue>TestCenterTimeZone</lip:tyvalue></lip:typename></lip:fieldlabel><lip:fielddata>-04:00</lip:fielddata></lip:temporalfield></lip:temporal><lip:temporal><lip:temporalfield><lip:fieldlabel><lip:typename><lip:tyvalue>AdminCode</lip:tyvalue></lip:typename></lip:fieldlabel><lip:fielddata>20140101B</lip:fielddata></lip:temporalfield></lip:temporal><lip:temporal><lip:temporalfield><lip:fieldlabel><lip:typename><lip:tyvalue>ProgramCode</lip:tyvalue></lip:typename></lip:fieldlabel><lip:fielddata>HSE</lip:fielddata></lip:temporalfield></lip:temporal><lip:temporal><lip:temporalfield><lip:fieldlabel><lip:typename><lip:tyvalue>TestCode</lip:tyvalue></lip:typename></lip:fieldlabel><lip:fielddata>903</lip:fielddata></lip:temporalfield></lip:temporal><lip:temporal><lip:temporalfield><lip:fieldlabel><lip:typename><lip:tyvalue>TEST_PKG</lip:tyvalue></lip:typename></lip:fieldlabel><lip:fielddata>HSE903PPT00053423PKG000</lip:fielddata></lip:temporalfield></lip:temporal><lip:temporal><lip:temporalfield><lip:fieldlabel><lip:typename><lip:tyvalue>SUBFORM</lip:tyvalue></lip:typename></lip:fieldlabel><lip:fielddata>000004-02-0000000001</lip:fielddata></lip:temporalfield></lip:temporal><lip:temporal><lip:temporalfield><lip:fieldlabel><lip:typename><lip:tyvalue>SystemFormCode</lip:tyvalue></lip:typename></lip:fieldlabel><lip:fielddata>144121</lip:fielddata></lip:temporalfield></lip:temporal><lip:temporal><lip:temporalfield><lip:fieldlabel><lip:typename><lip:tyvalue>DeliveryMode</lip:tyvalue></lip:typename></lip:fieldlabel><lip:fielddata>PBT</lip:fielddata></lip:temporalfield></lip:temporal><lip:temporal><lip:temporalfield><lip:fieldlabel><lip:typename><lip:tyvalue>OperationalCRCountReportedToRatingSystem</lip:tyvalue></lip:typename></lip:fieldlabel><lip:fielddata>0</lip:fielddata></lip:temporalfield></lip:temporal><lip:temporal><lip:temporalfield><lip:fieldlabel><lip:typename><lip:tyvalue>NonOperationalCRCountReportedToRatingSystem</lip:tyvalue></lip:typename></lip:fieldlabel><lip:fielddata>0</lip:fielddata></lip:temporalfield></lip:temporal><lip:temporal><lip:temporalfield><lip:fieldlabel><lip:typename><lip:tyvalue>CandidateScoreStatus</lip:tyvalue></lip:typename></lip:fieldlabel><lip:fielddata>RPTBL</lip:fielddata></lip:temporalfield></lip:temporal><lip:temporal><lip:temporalfield><lip:fieldlabel><lip:typename><lip:tyvalue>ScoreIndicator</lip:tyvalue></lip:typename></lip:fieldlabel><lip:fielddata>1</lip:fielddata></lip:temporalfield></lip:temporal></lip:contentype><lip:ext_identification><lip:address><lip:pobox /><lip:street /></lip:address><lip:demographics /></lip:ext_identification></lip:identification></context><testResult identifier="20140101B"><outcomeVariable baseType="integer" cardinality="single" identifier="TerminationType"><value fieldIdentifier="0036630640060010" /></outcomeVariable><outcomeVariable baseType="integer" cardinality="single" identifier="TerminationType"><value fieldIdentifier="000004-02-0000000001" /></outcomeVariable><outcomeVariable baseType="integer" cardinality="single" identifier="TerminationType"><value fieldIdentifier="1" /></outcomeVariable><outcomeVariable identifier="Life" normalMinimum="0" normalMaximum="25" cardinality="single" baseType="float"><value fieldIdentifier="002">5</value></outcomeVariable><outcomeVariable identifier="Phys" normalMinimum="0" normalMaximum="17" cardinality="single" baseType="float"><value fieldIdentifier="003">3</value></outcomeVariable><outcomeVariable identifier="Earth" normalMinimum="0" normalMaximum="8" cardinality="single" baseType="float"><value fieldIdentifier="004">1</value></outcomeVariable><outcomeVariable identifier="Total" normalMinimum="0" normalMaximum="50" cardinality="single" baseType="float"><value fieldIdentifier="050">9</value></outcomeVariable><outcomeVariable identifier="Total_SA" normalMinimum="1" normalMaximum="20" cardinality="single" baseType="float"><value fieldIdentifier="150">3</value></outcomeVariable><outcomeVariable identifier="Life_NA" normalMinimum="0" normalMaximum="25" cardinality="single" baseType="float"><value fieldIdentifier="151">25</value></outcomeVariable><outcomeVariable identifier="Phys_NA" normalMinimum="0" normalMaximum="17" cardinality="single" baseType="float"><value fieldIdentifier="152">17</value></outcomeVariable><outcomeVariable identifier="Earth_NA" normalMinimum="0" normalMaximum="8" cardinality="single" baseType="float"><value fieldIdentifier="153">8</value></outcomeVariable><outcomeVariable identifier="PF_MC" normalMinimum="0" normalMaximum="1" cardinality="single" baseType="float"><value fieldIdentifier="501">0</value></outcomeVariable><outcomeVariable identifier="CL_RGDY" normalMinimum="0" normalMaximum="1" cardinality="single" baseType="float"><value fieldIdentifier="502">0</value></outcomeVariable><outcomeVariable identifier="Scale_CR" normalMinimum="1" normalMaximum="20" cardinality="single" baseType="float"><value fieldIdentifier="600">3</value></outcomeVariable></testResult><itemResult identifier="VF881600" datestamp="2014-01-01T00:00:00Z" sessionStatus="final"><responseVariable identifier="CandidateResponse" cardinality="single" baseType="integer"><candidateResponse><value>1</value></candidateResponse></responseVariable><outcomeVariable identifier="EditCode" cardinality="single" baseType="integer"><value>0</value></outcomeVariable><outcomeVariable identifier="Score" cardinality="single" baseType="integer"><value>0.00</value></outcomeVariable></itemResult><itemResult identifier="VF882565" datestamp="2014-01-01T00:00:00Z" sessionStatus="final"><responseVariable identifier="CandidateResponse" cardinality="single" baseType="integer"><candidateResponse><value>1</value></candidateResponse></responseVariable><outcomeVariable identifier="EditCode" cardinality="single" baseType="integer"><value>0</value></outcomeVariable><outcomeVariable identifier="Score" cardinality="single" baseType="integer"><value>0.00</value></outcomeVariable></itemResult><itemResult identifier="VF881607" datestamp="2014-01-01T00:00:00Z" sessionStatus="final"><responseVariable identifier="CandidateResponse" cardinality="single" baseType="integer"><candidateResponse><value>1</value></candidateResponse></responseVariable><outcomeVariable identifier="EditCode" cardinality="single" baseType="integer"><value>0</value></outcomeVariable><outcomeVariable identifier="Score" cardinality="single" baseType="integer"><value>0.00</value></outcomeVariable></itemResult><itemResult identifier="VF881678" datestamp="2014-01-01T00:00:00Z" sessionStatus="final"><responseVariable identifier="CandidateResponse" cardinality="single" baseType="integer"><candidateResponse><value>1</value></candidateResponse></responseVariable><outcomeVariable identifier="EditCode" cardinality="single" baseType="integer"><value>0</value></outcomeVariable><outcomeVariable identifier="Score" cardinality="single" baseType="integer"><value>0.00</value></outcomeVariable></itemResult><itemResult identifier="VF881082" datestamp="2014-01-01T00:00:00Z" sessionStatus="final"><responseVariable identifier="CandidateResponse" cardinality="single" baseType="integer"><candidateResponse><value>1</value></candidateResponse></responseVariable><outcomeVariable identifier="EditCode" cardinality="single" baseType="integer"><value>1</value></outcomeVariable><outcomeVariable identifier="Score" cardinality="single" baseType="integer"><value>1</value></outcomeVariable></itemResult><itemResult identifier="VF881083" datestamp="2014-01-01T00:00:00Z" sessionStatus="final"><responseVariable identifier="CandidateResponse" cardinality="single" baseType="integer"><candidateResponse><value>1</value></candidateResponse></responseVariable><outcomeVariable identifier="EditCode" cardinality="single" baseType="integer"><value>1</value></outcomeVariable><outcomeVariable identifier="Score" cardinality="single" baseType="integer"><value>1</value></outcomeVariable></itemResult><itemResult identifier="VF881081" datestamp="2014-01-01T00:00:00Z" sessionStatus="final"><responseVariable identifier="CandidateResponse" cardinality="single" baseType="integer"><candidateResponse><value>1</value></candidateResponse></responseVariable><outcomeVariable identifier="EditCode" cardinality="single" baseType="integer"><value>0</value></outcomeVariable><outcomeVariable identifier="Score" cardinality="single" baseType="integer"><value>0.00</value></outcomeVariable></itemResult><itemResult identifier="VF881544" datestamp="2014-01-01T00:00:00Z" sessionStatus="final"><responseVariable identifier="CandidateResponse" cardinality="single" baseType="integer"><candidateResponse><value>2</value></candidateResponse></responseVariable><outcomeVariable identifier="EditCode" cardinality="single" baseType="integer"><value>0</value></outcomeVariable><outcomeVariable identifier="Score" cardinality="single" baseType="integer"><value>0.00</value></outcomeVariable></itemResult><itemResult identifier="VF881541" datestamp="2014-01-01T00:00:00Z" sessionStatus="final"><responseVariable identifier="CandidateResponse" cardinality="single" baseType="integer"><candidateResponse><value>3</value></candidateResponse></responseVariable><outcomeVariable identifier="EditCode" cardinality="single" baseType="integer"><value>0</value></outcomeVariable><outcomeVariable identifier="Score" cardinality="single" baseType="integer"><value>0.00</value></outcomeVariable></itemResult><itemResult identifier="VF881543" datestamp="2014-01-01T00:00:00Z" sessionStatus="final"><responseVariable identifier="CandidateResponse" cardinality="single" baseType="integer"><candidateResponse><value>4</value></candidateResponse></responseVariable><outcomeVariable identifier="EditCode" cardinality="single" baseType="integer"><value>1</value></outcomeVariable><outcomeVariable identifier="Score" cardinality="single" baseType="integer"><value>1</value></outcomeVariable></itemResult><itemResult identifier="VF881545" datestamp="2014-01-01T00:00:00Z" sessionStatus="final"><responseVariable identifier="CandidateResponse" cardinality="single" baseType="integer"><candidateResponse><value>3</value></candidateResponse></responseVariable><outcomeVariable identifier="EditCode" cardinality="single" baseType="integer"><value>0</value></outcomeVariable><outcomeVariable identifier="Score" cardinality="single" baseType="integer"><value>0.00</value></outcomeVariable></itemResult><itemResult identifier="VF881542" datestamp="2014-01-01T00:00:00Z" sessionStatus="final"><responseVariable identifier="CandidateResponse" cardinality="single" baseType="integer"><candidateResponse><value>3</value></candidateResponse></responseVariable><outcomeVariable identifier="EditCode" cardinality="single" baseType="integer"><value>0</value></outcomeVariable><outcomeVariable identifier="Score" cardinality="single" baseType="integer"><value>0.00</value></outcomeVariable></itemResult><itemResult identifier="VF881942" datestamp="2014-01-01T00:00:00Z" sessionStatus="final"><responseVariable identifier="CandidateResponse" cardinality="single" baseType="integer"><candidateResponse><value>3</value></candidateResponse></responseVariable><outcomeVariable identifier="EditCode" cardinality="single" baseType="integer"><value>0</value></outcomeVariable><outcomeVariable identifier="Score" cardinality="single" baseType="integer"><value>0.00</value></outcomeVariable></itemResult><itemResult identifier="VF881941" datestamp="2014-01-01T00:00:00Z" sessionStatus="final"><responseVariable identifier="CandidateResponse" cardinality="single" baseType="integer"><candidateResponse><value>4</value></candidateResponse></responseVariable><outcomeVariable identifier="EditCode" cardinality="single" baseType="integer"><value>0</value></outcomeVariable><outcomeVariable identifier="Score" cardinality="single" baseType="integer"><value>0.00</value></outcomeVariable></itemResult><itemResult identifier="VF881943" datestamp="2014-01-01T00:00:00Z" sessionStatus="final"><responseVariable identifier="CandidateResponse" cardinality="single" baseType="integer"><candidateResponse><value>2</value></candidateResponse></responseVariable><outcomeVariable identifier="EditCode" cardinality="single" baseType="integer"><value>1</value></outcomeVariable><outcomeVariable identifier="Score" cardinality="single" baseType="integer"><value>1</value></outcomeVariable></itemResult><itemResult identifier="VF882630" datestamp="2014-01-01T00:00:00Z" sessionStatus="final"><responseVariable identifier="CandidateResponse" cardinality="single" baseType="integer"><candidateResponse><value>1</value></candidateResponse></responseVariable><outcomeVariable identifier="EditCode" cardinality="single" baseType="integer"><value>0</value></outcomeVariable><outcomeVariable identifier="Score" cardinality="single" baseType="integer"><value>0.00</value></outcomeVariable></itemResult><itemResult identifier="VF881853" datestamp="2014-01-01T00:00:00Z" sessionStatus="final"><responseVariable identifier="CandidateResponse" cardinality="single" baseType="integer"><candidateResponse><value>1</value></candidateResponse></responseVariable><outcomeVariable identifier="EditCode" cardinality="single" baseType="integer"><value>0</value></outcomeVariable><outcomeVariable identifier="Score" cardinality="single" baseType="integer"><value>0.00</value></outcomeVariable></itemResult><itemResult identifier="VF881442" datestamp="2014-01-01T00:00:00Z" sessionStatus="final"><responseVariable identifier="CandidateResponse" cardinality="single" baseType="integer"><candidateResponse><value>2</value></candidateResponse></responseVariable><outcomeVariable identifier="EditCode" cardinality="single" baseType="integer"><value>0</value></outcomeVariable><outcomeVariable identifier="Score" cardinality="single" baseType="integer"><value>0.00</value></outcomeVariable></itemResult><itemResult identifier="VF881441" datestamp="2014-01-01T00:00:00Z" sessionStatus="final"><responseVariable identifier="CandidateResponse" cardinality="single" baseType="integer"><candidateResponse><value>2</value></candidateResponse></responseVariable><outcomeVariable identifier="EditCode" cardinality="single" baseType="integer"><value>1</value></outcomeVariable><outcomeVariable identifier="Score" cardinality="single" baseType="integer"><value>1</value></outcomeVariable></itemResult><itemResult identifier="VF881440" datestamp="2014-01-01T00:00:00Z" sessionStatus="final"><responseVariable identifier="CandidateResponse" cardinality="single" baseType="integer"><candidateResponse><value>3</value></candidateResponse></responseVariable><outcomeVariable identifier="EditCode" cardinality="single" baseType="integer"><value>0</value></outcomeVariable><outcomeVariable identifier="Score" cardinality="single" baseType="integer"><value>0.00</value></outcomeVariable></itemResult><itemResult identifier="VF881445" datestamp="2014-01-01T00:00:00Z" sessionStatus="final"><responseVariable identifier="CandidateResponse" cardinality="single" baseType="integer"><candidateResponse><value>4</value></candidateResponse></responseVariable><outcomeVariable identifier="EditCode" cardinality="single" baseType="integer"><value>0</value></outcomeVariable><outcomeVariable identifier="Score" cardinality="single" baseType="integer"><value>0.00</value></outcomeVariable></itemResult><itemResult identifier="VF881444" datestamp="2014-01-01T00:00:00Z" sessionStatus="final"><responseVariable identifier="CandidateResponse" cardinality="single" baseType="integer"><candidateResponse><value>1</value></candidateResponse></responseVariable><outcomeVariable identifier="EditCode" cardinality="single" baseType="integer"><value>0</value></outcomeVariable><outcomeVariable identifier="Score" cardinality="single" baseType="integer"><value>0.00</value></outcomeVariable></itemResult><itemResult identifier="VF881443" datestamp="2014-01-01T00:00:00Z" sessionStatus="final"><responseVariable identifier="CandidateResponse" cardinality="single" baseType="integer"><candidateResponse><value>2</value></candidateResponse></responseVariable><outcomeVariable identifier="EditCode" cardinality="single" baseType="integer"><value>0</value></outcomeVariable><outcomeVariable identifier="Score" cardinality="single" baseType="integer"><value>0.00</value></outcomeVariable></itemResult><itemResult identifier="VF882551" datestamp="2014-01-01T00:00:00Z" sessionStatus="final"><responseVariable identifier="CandidateResponse" cardinality="single" baseType="integer"><candidateResponse><value>3</value></candidateResponse></responseVariable><outcomeVariable identifier="EditCode" cardinality="single" baseType="integer"><value>1</value></outcomeVariable><outcomeVariable identifier="Score" cardinality="single" baseType="integer"><value>1</value></outcomeVariable></itemResult><itemResult identifier="VF882550" datestamp="2014-01-01T00:00:00Z" sessionStatus="final"><responseVariable identifier="CandidateResponse" cardinality="single" baseType="integer"><candidateResponse><value>4</value></candidateResponse></responseVariable><outcomeVariable identifier="EditCode" cardinality="single" baseType="integer"><value>1</value></outcomeVariable><outcomeVariable identifier="Score" cardinality="single" baseType="integer"><value>1</value></outcomeVariable></itemResult><itemResult identifier="VF882406" datestamp="2014-01-01T00:00:00Z" sessionStatus="final"><responseVariable identifier="CandidateResponse" cardinality="single" baseType="integer"><candidateResponse><value>1</value></candidateResponse></responseVariable><outcomeVariable identifier="EditCode" cardinality="single" baseType="integer"><value>0</value></outcomeVariable><outcomeVariable identifier="Score" cardinality="single" baseType="integer"><value>0.00</value></outcomeVariable></itemResult><itemResult identifier="VF882405" datestamp="2014-01-01T00:00:00Z" sessionStatus="final"><responseVariable identifier="CandidateResponse" cardinality="single" baseType="integer"><candidateResponse><value>1</value></candidateResponse></responseVariable><outcomeVariable identifier="EditCode" cardinality="single" baseType="integer"><value>1</value></outcomeVariable><outcomeVariable identifier="Score" cardinality="single" baseType="integer"><value>1</value></outcomeVariable></itemResult><itemResult identifier="VF882648" datestamp="2014-01-01T00:00:00Z" sessionStatus="final"><responseVariable identifier="CandidateResponse" cardinality="single" baseType="integer"><candidateResponse><value>2</value></candidateResponse></responseVariable><outcomeVariable identifier="EditCode" cardinality="single" baseType="integer"><value>0</value></outcomeVariable><outcomeVariable identifier="Score" cardinality="single" baseType="integer"><value>0.00</value></outcomeVariable></itemResult><itemResult identifier="VF882685" datestamp="2014-01-01T00:00:00Z" sessionStatus="final"><responseVariable identifier="CandidateResponse" cardinality="single" baseType="integer"><candidateResponse><value>3</value></candidateResponse></responseVariable><outcomeVariable identifier="EditCode" cardinality="single" baseType="integer"><value>0</value></outcomeVariable><outcomeVariable identifier="Score" cardinality="single" baseType="integer"><value>0.00</value></outcomeVariable></itemResult><itemResult identifier="VF881325" datestamp="2014-01-01T00:00:00Z" sessionStatus="final"><responseVariable identifier="CandidateResponse" cardinality="single" baseType="integer"><candidateResponse><value>4</value></candidateResponse></responseVariable><outcomeVariable identifier="EditCode" cardinality="single" baseType="integer"><value>0</value></outcomeVariable><outcomeVariable identifier="Score" cardinality="single" baseType="integer"><value>0.00</value></outcomeVariable></itemResult><itemResult identifier="VF881321" datestamp="2014-01-01T00:00:00Z" sessionStatus="final"><responseVariable identifier="CandidateResponse" cardinality="single" baseType="integer"><candidateResponse><value>4</value></candidateResponse></responseVariable><outcomeVariable identifier="EditCode" cardinality="single" baseType="integer"><value>0</value></outcomeVariable><outcomeVariable identifier="Score" cardinality="single" baseType="integer"><value>0.00</value></outcomeVariable></itemResult><itemResult identifier="VF881323" datestamp="2014-01-01T00:00:00Z" sessionStatus="final"><responseVariable identifier="CandidateResponse" cardinality="single" baseType="integer"><candidateResponse><value>3</value></candidateResponse></responseVariable><outcomeVariable identifier="EditCode" cardinality="single" baseType="integer"><value>0</value></outcomeVariable><outcomeVariable identifier="Score" cardinality="single" baseType="integer"><value>0.00</value></outcomeVariable></itemResult><itemResult identifier="VF881326" datestamp="2014-01-01T00:00:00Z" sessionStatus="final"><responseVariable identifier="CandidateResponse" cardinality="single" baseType="integer"><candidateResponse><value>3</value></candidateResponse></responseVariable><outcomeVariable identifier="EditCode" cardinality="single" baseType="integer"><value>0</value></outcomeVariable><outcomeVariable identifier="Score" cardinality="single" baseType="integer"><value>0.00</value></outcomeVariable></itemResult><itemResult identifier="VF881322" datestamp="2014-01-01T00:00:00Z" sessionStatus="final"><responseVariable identifier="CandidateResponse" cardinality="single" baseType="integer"><candidateResponse><value>2</value></candidateResponse></responseVariable><outcomeVariable identifier="EditCode" cardinality="single" baseType="integer"><value>0</value></outcomeVariable><outcomeVariable identifier="Score" cardinality="single" baseType="integer"><value>0.00</value></outcomeVariable></itemResult><itemResult identifier="VF881324" datestamp="2014-01-01T00:00:00Z" sessionStatus="final"><responseVariable identifier="CandidateResponse" cardinality="single" baseType="integer"><candidateResponse><value>2</value></candidateResponse></responseVariable><outcomeVariable identifier="EditCode" cardinality="single" baseType="integer"><value>0</value></outcomeVariable><outcomeVariable identifier="Score" cardinality="single" baseType="integer"><value>0.00</value></outcomeVariable></itemResult><itemResult identifier="VF881327" datestamp="2014-01-01T00:00:00Z" sessionStatus="final"><responseVariable identifier="CandidateResponse" cardinality="single" baseType="integer"><candidateResponse><value>1</value></candidateResponse></responseVariable><outcomeVariable identifier="EditCode" cardinality="single" baseType="integer"><value>0</value></outcomeVariable><outcomeVariable identifier="Score" cardinality="single" baseType="integer"><value>0.00</value></outcomeVariable></itemResult><itemResult identifier="VF882425" datestamp="2014-01-01T00:00:00Z" sessionStatus="final"><responseVariable identifier="CandidateResponse" cardinality="single" baseType="integer"><candidateResponse><value>1</value></candidateResponse></responseVariable><outcomeVariable identifier="EditCode" cardinality="single" baseType="integer"><value>0</value></outcomeVariable><outcomeVariable identifier="Score" cardinality="single" baseType="integer"><value>0.00</value></outcomeVariable></itemResult><itemResult identifier="VF882419" datestamp="2014-01-01T00:00:00Z" sessionStatus="final"><responseVariable identifier="CandidateResponse" cardinality="single" baseType="integer"><candidateResponse><value>2</value></candidateResponse></responseVariable><outcomeVariable identifier="EditCode" cardinality="single" baseType="integer"><value>0</value></outcomeVariable><outcomeVariable identifier="Score" cardinality="single" baseType="integer"><value>0.00</value></outcomeVariable></itemResult><itemResult identifier="VF882420" datestamp="2014-01-01T00:00:00Z" sessionStatus="final"><responseVariable identifier="CandidateResponse" cardinality="single" baseType="integer"><candidateResponse><value>2</value></candidateResponse></responseVariable><outcomeVariable identifier="EditCode" cardinality="single" baseType="integer"><value>0</value></outcomeVariable><outcomeVariable identifier="Score" cardinality="single" baseType="integer"><value>0.00</value></outcomeVariable></itemResult><itemResult identifier="VF882423" datestamp="2014-01-01T00:00:00Z" sessionStatus="final"><responseVariable identifier="CandidateResponse" cardinality="single" baseType="integer"><candidateResponse><value>2</value></candidateResponse></responseVariable><outcomeVariable identifier="EditCode" cardinality="single" baseType="integer"><value>0</value></outcomeVariable><outcomeVariable identifier="Score" cardinality="single" baseType="integer"><value>0.00</value></outcomeVariable></itemResult><itemResult identifier="VF882421" datestamp="2014-01-01T00:00:00Z" sessionStatus="final"><responseVariable identifier="CandidateResponse" cardinality="single" baseType="integer"><candidateResponse><value>3</value></candidateResponse></responseVariable><outcomeVariable identifier="EditCode" cardinality="single" baseType="integer"><value>0</value></outcomeVariable><outcomeVariable identifier="Score" cardinality="single" baseType="integer"><value>0.00</value></outcomeVariable></itemResult><itemResult identifier="VF882424" datestamp="2014-01-01T00:00:00Z" sessionStatus="final"><responseVariable identifier="CandidateResponse" cardinality="single" baseType="integer"><candidateResponse><value>3</value></candidateResponse></responseVariable><outcomeVariable identifier="EditCode" cardinality="single" baseType="integer"><value>0</value></outcomeVariable><outcomeVariable identifier="Score" cardinality="single" baseType="integer"><value>0.00</value></outcomeVariable></itemResult><itemResult identifier="VF882422" datestamp="2014-01-01T00:00:00Z" sessionStatus="final"><responseVariable identifier="CandidateResponse" cardinality="single" baseType="integer"><candidateResponse><value>1</value></candidateResponse></responseVariable><outcomeVariable identifier="EditCode" cardinality="single" baseType="integer"><value>0</value></outcomeVariable><outcomeVariable identifier="Score" cardinality="single" baseType="integer"><value>0.00</value></outcomeVariable></itemResult><itemResult identifier="VF882190" datestamp="2014-01-01T00:00:00Z" sessionStatus="final"><responseVariable identifier="CandidateResponse" cardinality="single" baseType="integer"><candidateResponse><value>1</value></candidateResponse></responseVariable><outcomeVariable identifier="EditCode" cardinality="single" baseType="integer"><value>0</value></outcomeVariable><outcomeVariable identifier="Score" cardinality="single" baseType="integer"><value>0.00</value></outcomeVariable></itemResult><itemResult identifier="VF882188" datestamp="2014-01-01T00:00:00Z" sessionStatus="final"><responseVariable identifier="CandidateResponse" cardinality="single" baseType="integer"><candidateResponse><value>2</value></candidateResponse></responseVariable><outcomeVariable identifier="EditCode" cardinality="single" baseType="integer"><value>0</value></outcomeVariable><outcomeVariable identifier="Score" cardinality="single" baseType="integer"><value>0.00</value></outcomeVariable></itemResult><itemResult identifier="VF882186" datestamp="2014-01-01T00:00:00Z" sessionStatus="final"><responseVariable identifier="CandidateResponse" cardinality="single" baseType="integer"><candidateResponse><value>2</value></candidateResponse></responseVariable><outcomeVariable identifier="EditCode" cardinality="single" baseType="integer"><value>0</value></outcomeVariable><outcomeVariable identifier="Score" cardinality="single" baseType="integer"><value>0.00</value></outcomeVariable></itemResult><itemResult identifier="VF882184" datestamp="2014-01-01T00:00:00Z" sessionStatus="final"><responseVariable identifier="CandidateResponse" cardinality="single" baseType="integer"><candidateResponse><value>3</value></candidateResponse></responseVariable><outcomeVariable identifier="EditCode" cardinality="single" baseType="integer"><value>0</value></outcomeVariable><outcomeVariable identifier="Score" cardinality="single" baseType="integer"><value>0.00</value></outcomeVariable></itemResult><itemResult identifier="VF882189" datestamp="2014-01-01T00:00:00Z" sessionStatus="final"><responseVariable identifier="CandidateResponse" cardinality="single" baseType="integer"><candidateResponse><value>4</value></candidateResponse></responseVariable><outcomeVariable identifier="EditCode" cardinality="single" baseType="integer"><value>0</value></outcomeVariable><outcomeVariable identifier="Score" cardinality="single" baseType="integer"><value>0.00</value></outcomeVariable></itemResult><itemResult identifier="VF882187" datestamp="2014-01-01T00:00:00Z" sessionStatus="final"><responseVariable identifier="CandidateResponse" cardinality="single" baseType="integer"><candidateResponse><value>1</value></candidateResponse></responseVariable><outcomeVariable identifier="EditCode" cardinality="single" baseType="integer"><value>1</value></outcomeVariable><outcomeVariable identifier="Score" cardinality="single" baseType="integer"><value>1</value></outcomeVariable></itemResult><itemResult identifier="VF882185" datestamp="2014-01-01T00:00:00Z" sessionStatus="final"><responseVariable identifier="CandidateResponse" cardinality="single" baseType="integer"><candidateResponse><value>1</value></candidateResponse></responseVariable><outcomeVariable identifier="EditCode" cardinality="single" baseType="integer"><value>0</value></outcomeVariable><outcomeVariable identifier="Score" cardinality="single" baseType="integer"><value>0.00</value></outcomeVariable></itemResult></assessmentResult>
</assessmentResults>